cs/imageutils.py
cs.imageutils-20240422.1.dist-info/METADATA
cs.imageutils-20240422.1.dist-info/WHEEL
cs.imageutils-20240422.1.dist-info/top_level.txt
cs.imageutils-20240422.1.dist-info/RECORD
