Metadata-Version: 2.1
Name: cs.imageutils
Version: 20240422.1
Summary: Various ad hoc image related utility functions and classes.
Author-email: Cameron Simpson <cs@cskk.id.au>
License: GNU General Public License v3 or later (GPLv3+)
Project-URL: URL, https://bitbucket.org/cameron_simpson/css/commits/all
Keywords: python3
Platform: UNKNOWN
Classifier: Development Status :: 5 - Production/Stable
Classifier: Environment :: Console
Classifier: Intended Audience :: Developers
Classifier: Programming Language :: Python :: 3
Classifier: Topic :: Multimedia :: Graphics :: Graphics Conversion
Classifier: Operating System :: OS Independent
Classifier: License :: OSI Approved :: GNU General Public License v3 or later (GPLv3+)
Requires-Dist: Pillow
Requires-Dist: cs.cache >=20240422.1
Requires-Dist: cs.deco >=20240412
Requires-Dist: cs.pfx >=20240412
Requires-Dist: cs.psutils >=20240316
